cloud_governance/__init__.py
cloud_governance/cloud_management/__init__.py
cloud_governance/cloud_management/aws/__init__.py
cloud_governance/cloud_management/aws/long_run/__init__.py
cloud_governance/cloud_management/aws/long_run/ec2_long_run.py
cloud_governance/cloud_management/aws/long_run/monitor_long_run.py
cloud_governance/cloud_management/aws/long_run/tag_long_run.py
cloud_governance/cloud_management/aws/short_run/__init__.py
cloud_governance/cloud_management/aws/short_run/ec2_short_run.py
cloud_governance/cloud_management/monitor/__init__.py
cloud_governance/cloud_management/monitor/cloud_monitor.py
cloud_governance/common/__init__.py
cloud_governance/common/clouds/__init__.py
cloud_governance/common/clouds/aws/__init__.py
cloud_governance/common/clouds/aws/cloudtrail/__init__.py
cloud_governance/common/clouds/aws/cloudtrail/cloudtrail_operations.py
cloud_governance/common/clouds/aws/cloudwatch/__init__.py
cloud_governance/common/clouds/aws/cloudwatch/cloudwatch_operations.py
cloud_governance/common/clouds/aws/cost_explorer/__init__.py
cloud_governance/common/clouds/aws/cost_explorer/cost_explorer_operations.py
cloud_governance/common/clouds/aws/dynamodb/__init__.py
cloud_governance/common/clouds/aws/dynamodb/dynamodb_operations.py
cloud_governance/common/clouds/aws/ec2/__init__.py
cloud_governance/common/clouds/aws/ec2/ec2_operations.py
cloud_governance/common/clouds/aws/iam/__init__.py
cloud_governance/common/clouds/aws/iam/iam_operations.py
cloud_governance/common/clouds/aws/price/__init__.py
cloud_governance/common/clouds/aws/price/price.py
cloud_governance/common/clouds/aws/price/resources_pricing.py
cloud_governance/common/clouds/aws/s3/__init__.py
cloud_governance/common/clouds/aws/s3/s3_operations.py
cloud_governance/common/clouds/aws/sts/__init__.py
cloud_governance/common/clouds/aws/sts/sts_oprations.py
cloud_governance/common/clouds/aws/utils/__init__.py
cloud_governance/common/clouds/aws/utils/utils.py
temprary_cloud_governance-1.1.65.dist-info/LICENSE
temprary_cloud_governance-1.1.65.dist-info/METADATA
temprary_cloud_governance-1.1.65.dist-info/WHEEL
temprary_cloud_governance-1.1.65.dist-info/top_level.txt
temprary_cloud_governance-1.1.65.dist-info/RECORD
