Metadata-Version: 2.1
Name: temprary-cloud-governance
Version: 1.1.65
Summary: Cloud Governance Tool
Home-page: https://github.com/redhat-performance/cloud-governance
Author: Red Hat
Author-email: ebattat@redhat.com, athiruma@redhat.com
License: Apache License 2.0
Platform: UNKNOWN
Classifier: License :: OSI Approved :: Apache Software License
Classifier: Programming Language :: Python :: 3
Classifier: Programming Language :: Python :: 3.6
Classifier: Programming Language :: Python :: 3.7
Classifier: Programming Language :: Python :: 3.8
Classifier: Programming Language :: Python :: 3.9
Classifier: Programming Language :: Python :: 3.10
License-File: LICENSE
Requires-Dist: attrs (==21.4.0)
Requires-Dist: azure-identity (==1.12.0)
Requires-Dist: azure-mgmt-costmanagement (==3.0.0)
Requires-Dist: azure-mgmt-subscription (==3.1.1)
Requires-Dist: botocore (==1.29.1)
Requires-Dist: boto3 (==1.26.1)
Requires-Dist: elasticsearch (==7.11.0)
Requires-Dist: elasticsearch-dsl (==7.4.0)
Requires-Dist: google-api-python-client (==2.57.0)
Requires-Dist: google-auth-httplib2 (==0.1.0)
Requires-Dist: google-auth-oauthlib (==0.5.2)
Requires-Dist: ibm-platform-services (==0.27.0)
Requires-Dist: myst-parser (==0.17.0)
Requires-Dist: pandas
Requires-Dist: PyGitHub (==1.55)
Requires-Dist: python-ldap (==3.4.2)
Requires-Dist: requests (==2.27.1)
Requires-Dist: retry (==0.9.2)
Requires-Dist: SoftLayer (==6.0.0)
Requires-Dist: sphinx (==4.5.0)
Requires-Dist: sphinx-rtd-theme (==1.0.0)
Requires-Dist: typing (==3.7.4.3)
Requires-Dist: typeguard (==2.13.3)
Requires-Dist: aiohttp (==3.8.1)
Requires-Dist: urllib3 (==1.26.7)
Requires-Dist: oauthlib (~=3.1.1)
